spindle/__init__.py
spindle/spindle.py
spindle/.idea/.gitignore
spindle/.idea/MANIFEST.in
spindle/.idea/misc.xml
spindle/.idea/modules.xml
spindle/.idea/spindle.iml
spindle/.idea/vcs.xml
spindle/.idea/workspace.xml
spindle/.idea/inspectionProfiles/Project_Default.xml
spindle/.idea/inspectionProfiles/profiles_settings.xml
spindle-0.0.0.dist-info/LICENSE.txt
spindle-0.0.0.dist-info/METADATA
spindle-0.0.0.dist-info/WHEEL
spindle-0.0.0.dist-info/top_level.txt
spindle-0.0.0.dist-info/RECORD
