Metadata-Version: 2.1
Name: spindle
Version: 0.0.0
Summary: Package for computing the properties of classical magnetic systems
Author: Gustavo Sáez Cruz
Author-email: virtualgluon@gmail.com
License: MIT
Requires-Python: >=3.12
License-File: LICENSE.txt
Requires-Dist: numpy
Requires-Dist: scipy
Requires-Dist: matplotlib
Requires-Dist: pathos
